README.rst
setup.py
toml_ply.py
toml_ply.egg-info/PKG-INFO
toml_ply.egg-info/SOURCES.txt
toml_ply.egg-info/dependency_links.txt
toml_ply.egg-info/requires.txt
toml_ply.egg-info/top_level.txt