Metadata-Version: 1.0
Name: toml-ply
Version: 0.0.4
Summary: TOML PLY parser
Home-page: https://github.com/marksteve/toml-ply
Author: Mark Steve Samson
Author-email: hello@marksteve.com
License: MIT
Platform: UNKNOWN
